setup.py
SBIcomm/SBIcomm.py
SBIcomm/__init__.py
SBIcomm.egg-info/PKG-INFO
SBIcomm.egg-info/SOURCES.txt
SBIcomm.egg-info/dependency_links.txt
SBIcomm.egg-info/requires.txt
SBIcomm.egg-info/top_level.txt