Metadata-Version: 1.0
Name: SBIcomm
Version: 0.1.3
Summary: Python Interface for SBI Securities
Home-page: UNKNOWN
Author: neka-nat
Author-email: nekanat.stock@gmail.com
License: UNKNOWN
Platform: UNKNOWN
